Metadata-Version: 2.1
Name: persia
Version: 0.1.dev251
Summary: PersiaML Python Library
Home-page: https://github.com/PersiaML/PersiaML
Author: Kuaishou AI Platform Persia Team
Author-email: admin@mail.xrlian.com
Requires-Python: >=3.6
License-File: LICENSE
